scalewob/__init__.py
scalewob/api.py
scalewob/automation.py
scalewob/exceptions.py
scalewob-0.11.0.dist-info/WHEEL
scalewob-0.11.0.dist-info/METADATA
scalewob-0.11.0.dist-info/RECORD
