Metadata-Version: 2.3
Name: scalewob
Version: 0.11.0
Summary: Python SDK for evaluating in ScaleWoB: Scalable world-of-bit that revolutionizes the evaluation of Computer-Use Agents.
Keywords: automation,evaluation,computer-use-agents,selenium,benchmark
Author: Guohong Liu
Author-email: Guohong Liu <112002598+Zsbyqx20@users.noreply.github.com>
License: MIT
Classifier: Development Status :: 3 - Alpha
Classifier: Intended Audience :: Developers
Classifier: Intended Audience :: Science/Research
Classifier: License :: OSI Approved :: MIT License
Classifier: Programming Language :: Python :: 3
Classifier: Programming Language :: Python :: 3.12
Classifier: Programming Language :: Python :: 3.13
Classifier: Topic :: Software Development :: Testing
Classifier: Topic :: Scientific/Engineering :: Artificial Intelligence
Requires-Dist: jsonschema>=4.26.0
Requires-Dist: pillow>=12.1.0
Requires-Dist: requests>=2.32.5
Requires-Dist: selenium>=4.39.0
Requires-Python: >=3.12
Project-URL: Homepage, https://github.com/ScaleWoB/ScaleWoB
Project-URL: Repository, https://github.com/ScaleWoB/ScaleWoB
Project-URL: Documentation, https://github.com/ScaleWoB/ScaleWoB#readme
Project-URL: Bug Tracker, https://github.com/ScaleWoB/ScaleWoB/issues
